jetio_auth/__init__.py
jetio_auth/auth_policy.py
jetio_auth/auth_router.py
jetio_auth/email_service.py
jetio_auth/mixins.py
jetio_auth/tokens.py
jetio_auth/utils.py
jetio_auth/templates/emails/activation.html
jetio_auth/templates/emails/password_reset.html
jetio_auth/templates/emails/password_reset_success.html
jetio_auth-0.2.3.dist-info/licenses/LICENSE
tests/__init__.py
tests/conftest.py
tests/test_auth_router.py
tests/test_edge_cases.py
tests/test_email_features.py
tests/test_policies.py
tests/test_utils.py
jetio_auth-0.2.3.dist-info/METADATA
jetio_auth-0.2.3.dist-info/WHEEL
jetio_auth-0.2.3.dist-info/top_level.txt
jetio_auth-0.2.3.dist-info/RECORD
