Metadata-Version: 2.4
Name: jetio-auth
Version: 0.2.3
Summary: Seamless, zero-config authentication and authorization for the Jetio framework.
Home-page: https://github.com/cehstephen/jetio-auth
Author: Stephen Tete
Author-email: cehtete@gmail.com
Project-URL: Homepage, https://jetio.org
Project-URL: Bug Tracker, https://github.com/cehstephen/jetio-auth/issues
Classifier: Development Status :: 4 - Beta
Classifier: Intended Audience :: Developers
Classifier: License :: OSI Approved :: BSD License
Classifier: Operating System :: OS Independent
Classifier: Programming Language :: Python :: 3
Classifier: Programming Language :: Python :: 3.9
Classifier: Programming Language :: Python :: 3.10
Classifier: Programming Language :: Python :: 3.11
Classifier: Framework :: AsyncIO
Requires-Python: >=3.9
License-File: LICENSE
Requires-Dist: passlib[bcrypt]>=1.7.4
Requires-Dist: aiosmtplib>=5.0.0
Dynamic: license-file
